{
  "type": "capability",
  "name": "sculpting",
  "folder": null,
  "system": {
    "slug": "sculpting",
    "description": "<p>Vous comprenez et savez créer des objets esthétiques tels que des statues commémoratives militaires ou des bols de prière obun.</p>",
    "type": "lores",
    "category": "arts",
    "preconditions": []
  },
  "_id": "RW4SohDCH18qOYp3",
  "img": "icons/sundries/scrolls/scroll-bound-blue-red.webp",
  "effects": [],
  "flags": {},
  "_stats": {
    "compendiumSource": null,
    "duplicateSource": null,
    "exportSource": null,
    "coreVersion": "13.350",
    "systemId": "fading-suns-4",
    "systemVersion": "0.0.1",
    "createdTime": 1761066203458,
    "modifiedTime": 1761066203458,
    "lastModifiedBy": "ef54fWvGiyPGgegN"
  },
  "ownership": {
    "default": 0,
    "ef54fWvGiyPGgegN": 3
  },
  "sort": 0,
  "_key": "!items!RW4SohDCH18qOYp3"
}