{
  "type": "armor",
  "name": "leather_jerkin",
  "folder": "4geLGbwgCVI1GW3v",
  "system": {
    "slug": "leather_jerkin",
    "description": "",
    "curio": false,
    "agora": "",
    "quality": "standard",
    "size": "none",
    "features": [],
    "fb": 5,
    "tl": 1,
    "capability": null,
    "res": 2,
    "eshieldCompatibility": "ea",
    "anti": [
      "shock",
      "slam"
    ],
    "techCompulsion": null
  },
  "_id": "78ihx1DOai95NaFP",
  "img": "icons/equipment/chest/breastplate-banded-blue.webp",
  "effects": [],
  "flags": {},
  "_stats": {
    "compendiumSource": null,
    "duplicateSource": null,
    "exportSource": null,
    "coreVersion": "13.350",
    "systemId": "fading-suns-4",
    "systemVersion": "0.0.1",
    "createdTime": 1760897547556,
    "modifiedTime": 1760897547556,
    "lastModifiedBy": "ef54fWvGiyPGgegN"
  },
  "ownership": {
    "default": 0,
    "ef54fWvGiyPGgegN": 3
  },
  "sort": 0,
  "_key": "!items!78ihx1DOai95NaFP"
}
