{
  "type": "curse",
  "name": "secretive",
  "folder": null,
  "system": {
    "slug": "secretive",
    "description": ""
  },
  "_id": "SAimKxNgYn1qM19P",
  "img": "icons/magic/symbols/mask-yellow-orange.webp",
  "effects": [
    {
      "disabled": false,
      "img": "icons/magic/symbols/mask-yellow-orange.webp",
      "type": "modifier",
      "changes": [],
      "duration": {
        "startTime": null,
        "combat": null
      },
      "description": "",
      "origin": null,
      "tint": "#ffffff",
      "transfer": true,
      "statuses": [],
      "flags": {},
      "_stats": {
        "compendiumSource": null,
        "duplicateSource": null,
        "exportSource": null,
        "coreVersion": "13.350",
        "systemId": "fading-suns-4",
        "systemVersion": "PLACEHOLDER",
        "lastModifiedBy": null
      },
      "name": "secretive",
      "_id": "sjYWexSnPF50Af9z",
      "system": {
        "valueType": "constant",
        "targetType": "characteristic",
        "target": "presence",
        "austerity": false,
        "context": "none",
        "value": "-2",
        "notes": "Around strangers"
      },
      "sort": 0,
      "_key": "!items.effects!SAimKxNgYn1qM19P.sjYWexSnPF50Af9z"
    }
  ],
  "flags": {},
  "_stats": {
    "compendiumSource": null,
    "duplicateSource": null,
    "exportSource": null,
    "coreVersion": "13.350",
    "systemId": "fading-suns-4",
    "systemVersion": "0.0.1",
    "createdTime": 1760907525715,
    "modifiedTime": 1760907525715,
    "lastModifiedBy": "ef54fWvGiyPGgegN"
  },
  "ownership": {
    "default": 0,
    "ef54fWvGiyPGgegN": 3
  },
  "sort": 0,
  "_key": "!items!SAimKxNgYn1qM19P"
}
